pytest_change_report.py
pytest_change_report-1.0.dist-info/LICENSE
pytest_change_report-1.0.dist-info/METADATA
pytest_change_report-1.0.dist-info/WHEEL
pytest_change_report-1.0.dist-info/entry_points.txt
pytest_change_report-1.0.dist-info/top_level.txt
pytest_change_report-1.0.dist-info/RECORD
