Metadata-Version: 2.1
Name: pytest-change-report
Version: 1.0
Summary: turn . into √，turn F into x
Home-page: https://github.com/yoyoketang/pytest-change-report
Author: yoyo
Author-email: 283340479@qq.com
License: proprietary
Keywords: pytest,py.test,pytest-change-report
Platform: UNKNOWN
Classifier: Framework :: Pytest
Classifier: Programming Language :: Python
Classifier: Topic :: Software Development :: Testing
Classifier: Programming Language :: Python :: 3.6
Requires-Dist: pytest
